cadbiom_gui/__init__.py
cadbiom_gui/__main__.py
cadbiom_gui/gt_gui/__init__.py
cadbiom_gui/gt_gui/chart_controler.py
cadbiom_gui/gt_gui/chart_misc_widgets.py
cadbiom_gui/gt_gui/chart_view.py
cadbiom_gui/gt_gui/charter.py
cadbiom_gui/gt_gui/charter_info.py
cadbiom_gui/gt_gui/edit_mvc.py
cadbiom_gui/gt_gui/layout.py
cadbiom_gui/gt_gui/chart_checker/__init__.py
cadbiom_gui/gt_gui/chart_checker/chart_checker_controler.py
cadbiom_gui/gt_gui/chart_glade/biosiged.glade
cadbiom_gui/gt_gui/chart_glade/button_frame.glade
cadbiom_gui/gt_gui/chart_glade/chart_simulator.glade
cadbiom_gui/gt_gui/chart_glade/charter.glade
cadbiom_gui/gt_gui/chart_glade/checker.glade
cadbiom_gui/gt_gui/chart_glade/checker_common.glade
cadbiom_gui/gt_gui/chart_glade/checker_solutions.glade
cadbiom_gui/gt_gui/chart_glade/consequence_form.glade
cadbiom_gui/gt_gui/chart_glade/dependency_graph.glade
cadbiom_gui/gt_gui/chart_glade/import_BioPAX_parameters.glade
cadbiom_gui/gt_gui/chart_glade/import_parameter.glade
cadbiom_gui/gt_gui/chart_glade/invariant_form.glade
cadbiom_gui/gt_gui/chart_glade/model_info.glade
cadbiom_gui/gt_gui/chart_glade/node_info.glade
cadbiom_gui/gt_gui/chart_glade/occurence_form.glade
cadbiom_gui/gt_gui/chart_glade/sequence_form.glade
cadbiom_gui/gt_gui/chart_glade/simu_places.glade
cadbiom_gui/gt_gui/chart_glade/static_analysis.glade
cadbiom_gui/gt_gui/chart_glade/trans_info.glade
cadbiom_gui/gt_gui/chart_simulator/__init__.py
cadbiom_gui/gt_gui/chart_simulator/chart_chrono.py
cadbiom_gui/gt_gui/chart_simulator/chart_simul_controler.py
cadbiom_gui/gt_gui/chart_static/__init__.py
cadbiom_gui/gt_gui/chart_static/chart_stat_controler.py
cadbiom_gui/gt_gui/graphics/__init__.py
cadbiom_gui/gt_gui/graphics/drawing_style.py
cadbiom_gui/gt_gui/images/favicon.ico
cadbiom_gui/gt_gui/images/input_node.png
cadbiom_gui/gt_gui/images/legend.png
cadbiom_gui/gt_gui/images/macro_node.png
cadbiom_gui/gt_gui/images/permanent_node.png
cadbiom_gui-0.3.dist-info/METADATA
cadbiom_gui-0.3.dist-info/RECORD
cadbiom_gui-0.3.dist-info/WHEEL
cadbiom_gui-0.3.dist-info/entry_points.txt
cadbiom_gui-0.3.dist-info/top_level.txt
