Metadata-Version: 2.1
Name: cadbiom-gui
Version: 0.3
Summary: GUI of Cadbiom software v0.3
Home-page: https://gitlab.inria.fr/pvignet/cadbiom
Author: pvignet
Author-email: pierre.vignet@irisa.fr
License: UNKNOWN
Platform: UNKNOWN
Classifier: Environment :: X11 Applications :: GTK
Classifier: Development Status :: 4 - Beta
Classifier: License :: OSI Approved :: GNU General Public License v2 or later (GPLv2+)
Classifier: Natural Language :: French
Classifier: Intended Audience :: Developers
Classifier: Operating System :: OS Independent
Classifier: Programming Language :: Python :: 2.7
Classifier: Topic :: Scientific/Engineering :: Bio-Informatics
Requires-Dist: cadbiom
Requires-Dist: pygraphviz
